{
  "platform": "agency-admin",
  "currentVersion": "1.1.0",
  "lastUpdated": "2026-07-05",
  "figmaUrl": "https://www.figma.com/design/264Gc7s2XLHjBZsr2HnBEe/-AGA--AGENCY-ADMIN?node-id=2-449",
  "sections": [
    {
      "key": "login-logout",
      "title": "Login / Logout",
      "stories": [
        {
          "id": "AGA-AUTH-1",
          "jiraKey": "AGENCY-40",
          "title": "[AGA] Login screen",
          "userStory": "Là Agency Admin (Đại lý), tôi muốn đăng nhập vào trang quản trị của đại lý thông qua URL riêng và tài khoản được GHN Super Admin cung cấp để có thể quản lý shop và đơn hàng.",
          "notes": [
            "URL đăng nhập được cấu hình tại bước tạo đại lý (AGENCY-14: [GSA] Đại lý - Tạo mới đại lý: Cấu hình URL trang Agency Admin)",
            "Tài khoản (username/password) được cấp bởi GHN Super Admin (AGENCY-15)",
            "Chưa hỗ trợ đăng ký tài khoản",
            "Tài khoản chỉ đăng nhập được trên đúng URL (slug) của đại lý"
          ],
          "userFlow": [
            "Agency Admin truy cập URL trang quản trị đại lý: https://admin-[slug].chotdon.ai",
            "Hệ thống xác định đại lý mà user đang truy cập dựa trên URL",
            "Agency Admin nhập Tên đăng nhập và Mật khẩu",
            "Nhấn \"Đăng nhập\"",
            "Hệ thống kiểm tra tài khoản hợp lệ và tài khoản thuộc đúng tenant (slug)",
            "Nếu hợp lệ → đăng nhập thành công và chuyển đến màn hình Quản lý shop",
            "Nếu không hợp lệ → hiển thị lỗi tương ứng"
          ],
          "acceptanceCriteria": [
            "AC1: Hệ thống hiển thị màn hình đăng nhập với các trường: Tên đăng nhập, Mật khẩu, Nút \"Đăng nhập\".",
            "AC2: Agency Admin chỉ có thể truy cập trang login thông qua URL đã được cấu hình cho đại lý.",
            "AC3: Khi Agency Admin thực hiện đăng nhập, hệ thống phải kiểm tra đồng thời: Username/password hợp lệ; Tài khoản thuộc đúng agency_id tương ứng với slug trên URL; Hệ thống phải xác định đúng đại lý (tenant) dựa trên slug trong URL.",
            "AC4: Điều kiện đăng nhập thành công: Username/password đúng VÀ tài khoản thuộc đúng tenant (slug) → Hệ thống cho phép đăng nhập.",
            "AC5: Trường hợp username/password đúng nhưng sai tenant (slug): Hệ thống từ chối đăng nhập; Hiển thị lỗi \"Tài khoản không thuộc hệ thống này\".",
            "AC6: Hệ thống không cho phép đăng nhập chéo giữa các tenant. Một tài khoản Agency Admin chỉ đăng nhập được tại đúng URL slug đã được cấu hình.",
            "AC7: Hệ thống không cung cấp chức năng đăng ký tài khoản.",
            "AC8: Sau khi đăng nhập thành công, hệ thống tạo và lưu session 7 ngày cho người dùng.",
            "AC9: Khi session hết hạn, Agency Admin bị đăng xuất và chuyển về màn hình login."
          ]
        }
      ]
    },
    {
      "key": "shops",
      "title": "Quản lý Shop",
      "stories": [
        {
          "id": "AGA-SHOP-1",
          "jiraKey": "AGENCY-42",
          "title": "[AGA] Shop - Danh sách shop: Xem danh sách shop",
          "userStory": "Là Agency Admin (Đại lý), tôi muốn xem và quản lý danh sách các shop thuộc đại lý của mình để có thể theo dõi hoạt động, kiểm soát trạng thái và thực hiện các thao tác quản lý shop.",
          "notes": [],
          "userFlow": [
            "Agency Admin truy cập menu Quản lý shop",
            "Hệ thống hiển thị danh sách tất cả shop thuộc đại lý",
            "Agency Admin có thể: Xem thông tin từng shop, Tìm kiếm shop (AGENCY-43), Phân trang danh sách, Tạo shop mới (AGENCY-45)"
          ],
          "acceptanceCriteria": [
            "AC1: Khi Agency Admin truy cập màn \"Quản lý shop\", hệ thống hiển thị danh sách shop thuộc đúng đại lý.",
            "AC2: Mỗi shop hiển thị các thông tin: Tên shop - Mã shop (shop_id), Chủ shop - Số điện thoại, Số đơn hàng, Tổng COD, Doanh thu.",
            "AC3: Agency Admin chỉ có thể xem các shop thuộc đại lý của mình, không thể truy cập shop của đại lý khác.",
            "AC4: Hệ thống hỗ trợ tìm kiếm không phân biệt chữ hoa/thường và theo từ khóa một phần.",
            "AC5: Hệ thống hỗ trợ phân trang danh sách shop.",
            "AC6: Agency Admin có thể chọn số lượng bản ghi hiển thị trên mỗi trang.",
            "AC7: Agency Admin có thể nhấn \"Tạo shop mới\" để chuyển sang màn tạo shop (AGENCY-45).",
            "AC8: Khi không có dữ liệu, hệ thống hiển thị trạng thái empty phù hợp."
          ]
        },
        {
          "id": "AGA-SHOP-2",
          "jiraKey": "AGENCY-43",
          "title": "[AGA] Shop - Danh sách shop: Search shop",
          "userStory": "Là Agency Admin (Đại lý), tôi muốn tìm kiếm shop trong danh sách shop thuộc đại lý của mình để nhanh chóng truy cập và quản lý shop cần thiết.",
          "notes": [],
          "userFlow": [],
          "acceptanceCriteria": [
            "AC1: Hệ thống hiển thị ô tìm kiếm tại màn \"Quản lý shop\".",
            "AC2: Agency Admin có thể nhập từ khóa để tìm kiếm shop.",
            "AC3: Hệ thống thực hiện tìm kiếm theo các trường: Tên shop, Mã shop (shop_id), Tên chủ shop, Số điện thoại shop.",
            "AC4: Kết quả tìm kiếm chỉ bao gồm các shop thuộc của Agency Admin đang đăng nhập.",
            "AC5: Hệ thống hỗ trợ tìm kiếm không phân biệt chữ hoa/thường và tìm kiếm theo một phần từ khóa (partial match).",
            "AC6: Khi không có kết quả phù hợp, hệ thống hiển thị trạng thái không tìm thấy dữ liệu.",
            "AC7: Khi xóa từ khóa tìm kiếm, hệ thống hiển thị lại toàn bộ danh sách shop."
          ]
        },
        {
          "id": "AGA-SHOP-3",
          "jiraKey": "AGENCY-45",
          "title": "[AGA] Shop - Tạo mới shop: Thông tin cơ bản",
          "userStory": "Là Agency Admin (Đại lý), tôi muốn nhập thông tin cơ bản của shop để tạo mới shop thuộc đại lý của mình, giúp các shop có thể sử dụng hệ thống để lên đơn.",
          "notes": [],
          "userFlow": [
            "Agency Admin truy cập màn \"Quản lý shop\"",
            "Agency Admin click \"Tạo shop mới\"",
            "Hệ thống hiển thị form \"Thông tin cơ bản\"",
            "Agency Admin nhập các thông tin: Thông tin chung, Cấu hình tài khoản shop đăng nhập (AGENCY-46)",
            "Agency Admin click \"Lưu\"",
            "Hệ thống validate dữ liệu",
            "Nếu hợp lệ → cho phép lưu shop",
            "Nếu không hợp lệ → hiển thị lỗi"
          ],
          "acceptanceCriteria": [
            "AC1: Agency Admin có thể truy cập màn tạo shop từ màn \"Quản lý shop\".",
            "AC2: Hệ thống hiển thị các field: Tên shop (bắt buộc), Tên chủ shop, Số điện thoại (bắt buộc), Địa chỉ lấy hàng (bắt buộc) gồm Số nhà/tên đường, Tỉnh/Thành, Quận/Huyện, Phường/Xã.",
            "AC3: Mã shop (shop_id) được hệ thống tự động generate. Gồm 6 ký tự, format: 3 chữ cái IN HOA + 3 số (ví dụ: ABC123, XDF908). Unique toàn hệ thống.",
            "AC5: Validate dữ liệu: Tên shop không được để trống, tối đa 255 ký tự. Số điện thoại không được để trống, đúng định dạng di động, unique trong phạm vi cùng agency. Địa chỉ không được để trống, phải chọn đủ Tỉnh/Thành → Quận/Huyện → Phường/Xã.",
            "AC6: Khi tạo shop thành công, hệ thống lưu shop_id (system generate), agency_id (từ Agency Admin đang đăng nhập). Trạng thái mặc định: Hoạt động.",
            "AC7: Hệ thống đảm bảo tenant isolation: Agency Admin chỉ tạo được shop thuộc đại lý của mình.",
            "AC9: Trường hợp nhập SĐT bị trùng trong cùng agency: Hệ thống hiển thị lỗi số điện thoại đã tồn tại trong đại lý, không cho phép tạo shop.",
            "AC10: Trường hợp dữ liệu không hợp lệ: Hiển thị message lỗi tại từng field, không cho submit."
          ]
        },
        {
          "id": "AGA-SHOP-4",
          "jiraKey": "AGENCY-46",
          "title": "[AGA] Shop - Tạo mới shop: Cấu hình User/Password cho chủ shop đăng nhập Web/App shop",
          "userStory": "Là Agency Admin (Đại lý), tôi muốn cấu hình tài khoản đăng nhập (username/password) cho shop để chủ shop có thể đăng nhập vào hệ thống Web/App và sử dụng dịch vụ.",
          "notes": [],
          "userFlow": [],
          "acceptanceCriteria": [
            "AC1: Hệ thống hiển thị section cấu hình tài khoản đăng nhập trong màn hình tạo shop.",
            "AC2: Username shop được cấu thành theo format: username = shop_id + \"-\" + {username do Agency Admin nhập}. shop_id do hệ thống generate (6 ký tự: 3 chữ in hoa + 3 số). Phần suffix được prefill sẵn bằng số điện thoại chủ shop, Agency Admin có thể edit lại.",
            "AC3: Agency Admin không được chỉnh sửa phần shop_id trong username. Chỉ được nhập phần phía sau dấu \"-\".",
            "AC4: Username là bắt buộc, không chứa ký tự đặc biệt (chỉ a-z, 0-9), unique toàn hệ thống.",
            "AC5: Khi username bị trùng: Hệ thống hiển thị lỗi \"Tên đăng nhập đã tồn tại\", không cho phép lưu.",
            "AC6: Password là bắt buộc, tối thiểu 8 ký tự, ít nhất 1 ký tự viết hoa, 1 ký tự viết thường, 1 ký tự số và 1 ký tự đặc biệt.",
            "AC7: Hệ thống hỗ trợ: Ẩn/hiện mật khẩu, Sao chép username, Sao chép mật khẩu.",
            "AC8: Khi submit hợp lệ, hệ thống lưu username, password mapping với shop_id và agency_id.",
            "AC9: Đảm bảo tenant isolation: Shop chỉ đăng nhập được vào hệ thống thuộc agency_id của mình.",
            "AC10: Khi dữ liệu không hợp lệ: Hiển thị lỗi tại từng field, không cho submit.",
            "AC11: Sau khi tạo thành công, tài khoản shop có thể sử dụng để đăng nhập Web shop (AGENCY-78) và App shop (AGENCY-79)."
          ]
        },
        {
          "id": "AGA-SHOP-5",
          "jiraKey": "",
          "title": "[AGA] Shop: View thông tin chi tiết shop",
          "userStory": "",
          "notes": [],
          "userFlow": [],
          "acceptanceCriteria": []
        },
        {
          "id": "AGA-SHOP-6",
          "jiraKey": "",
          "title": "[AGA] Shop - Tạo mới shop: Cấu hình dịch vụ",
          "userStory": "Là Agency Admin (Đại lý), tôi muốn cấu hình dịch vụ vận chuyển cho shop ngay khi tạo mới để xác định shop đó có thể sử dụng những dịch vụ nào và theo bảng giá nào.",
          "notes": [
            "Mỗi dịch vụ (Service) được kết nối với 1 GHN Shop ID — đây là Shop ID của tài khoản GHN, khác với shop_id của agency shop",
            "Shop có thể được gắn với nhiều dịch vụ, mỗi dịch vụ dùng 1 bảng giá riêng",
            "Nếu một dịch vụ không được chọn bảng giá → dịch vụ đó không khả dụng với shop này",
            "Section \"Cấu hình dịch vụ\" là Section 3 trong form tạo shop mới, sau \"Thông tin cơ bản\" (AGA-SHOP-3) và \"Cấu hình tài khoản\" (AGA-SHOP-4)"
          ],
          "userFlow": [
            "Agency Admin truy cập màn tạo shop mới",
            "Sau khi điền thông tin cơ bản và tài khoản đăng nhập, Agency Admin kéo xuống Section 3 \"Cấu hình dịch vụ\"",
            "Hệ thống hiển thị danh sách tất cả dịch vụ đang được cấu hình trong đại lý",
            "Với mỗi dịch vụ, Agency Admin chọn bảng giá từ dropdown",
            "Nếu không chọn bảng giá cho một dịch vụ, hệ thống hiển thị cảnh báo màu vàng \"Dịch vụ sẽ không khả dụng\"",
            "Agency Admin hoàn tất và submit form tạo shop"
          ],
          "acceptanceCriteria": [
            "AC1: Màn hình tạo shop mới có Section 3 \"Cấu hình dịch vụ\" nằm sau Section 1 (Thông tin cơ bản) và Section 2 (Cấu hình tài khoản).",
            "AC2: Section \"Cấu hình dịch vụ\" hiển thị danh sách tất cả dịch vụ vận chuyển đang active trong đại lý. Mỗi dịch vụ hiện tên dịch vụ, mã dịch vụ và dropdown chọn bảng giá.",
            "AC3: Dropdown bảng giá của mỗi dịch vụ chỉ liệt kê các bảng giá đang thuộc dịch vụ đó (không trộn bảng giá của dịch vụ khác).",
            "AC4: Khi Agency Admin chưa chọn bảng giá cho một dịch vụ, hệ thống hiển thị cảnh báo màu vàng bên dưới dịch vụ đó: \"Dịch vụ sẽ không khả dụng nếu không có bảng giá\".",
            "AC5: Agency Admin có thể bỏ qua việc chọn bảng giá cho một hoặc nhiều dịch vụ — không bắt buộc phải chọn đủ tất cả dịch vụ để submit form.",
            "AC6: Sau khi tạo shop thành công, hệ thống lưu mapping giữa shop và từng dịch vụ kèm bảng giá đã chọn. Dịch vụ không được chọn bảng giá sẽ không khả dụng với shop đó.",
            "AC7: Hệ thống đảm bảo tenant isolation: danh sách dịch vụ và bảng giá trong dropdown chỉ bao gồm dịch vụ/bảng giá thuộc đại lý của Agency Admin đang đăng nhập.",
            "AC8: Khi không có dịch vụ nào được cấu hình trong đại lý, Section \"Cấu hình dịch vụ\" hiển thị thông báo hướng dẫn Agency Admin thiết lập dịch vụ tại màn \"Thiết lập NVC\" trước."
          ],
          "status": "draft"
        },
        {
          "id": "AGA-SHOP-7",
          "jiraKey": "AGENCY-611",
          "title": "[AGA] Shop - Hiển thị Inactive khi shop tự xoá tài khoản",
          "status": "draft",
          "userStory": "Là Agency Admin, tôi muốn tự động thấy shop chuyển sang trạng thái Inactive khi shop đó tự xoá tài khoản, và có thể kích hoạt lại nếu cần, để tôi luôn nắm được tình trạng thực tế của danh sách shop mà không cần phải làm gì thêm.",
          "notes": [
            "Task này phụ thuộc AGENCY-610 — cần deploy song song hoặc AGENCY-610 trước",
            "Kích hoạt lại không yêu cầu shop đồng ý — Agency Admin có toàn quyền. Nhưng cần gửi email thông báo cho shop biết",
            "Không có thời hạn tự động xoá hẳn — shop Inactive tồn tại vô thời hạn cho đến khi có policy rõ ràng hơn"
          ],
          "userFlow": [
            "Shop hoàn thành xoá tài khoản (AGENCY-610) → system tự cập nhật status = inactive",
            "Agency Admin vào Quản lý shop → thấy shop đó hiển thị mờ với badge Inactive + ghi chú Tự xoá DD/MM",
            "Agency Admin không cần làm gì thêm",
            "(Tùy chọn) Nếu shop đổi ý liên hệ lại: Agency Admin vào chi tiết shop → nhấn Kích hoạt lại tài khoản",
            "Shop nhận email thông báo tài khoản đã được kích hoạt lại"
          ],
          "acceptanceCriteria": [
            "AC1: Ngay sau khi shop xoá tài khoản, danh sách shop phía Agency Admin tự động cập nhật — không cần F5.",
            "AC2: Row shop Inactive hiển thị: tên xám + badge Inactive + ghi chú Tự xoá DD/MM. Phân biệt rõ với shop Active.",
            "AC3: Agency Admin có thể click vào shop Inactive để xem chi tiết: lý do xoá, ghi chú, ngày xoá.",
            "AC4: Nút Kích hoạt lại tài khoản hoạt động: sau khi kích hoạt → status = Active, shop nhận email, row trở lại bình thường.",
            "AC5: Dữ liệu lịch sử của shop (đơn hàng, đối soát, COD) vẫn tra cứu được sau khi Inactive.",
            "AC6: Agency Admin không nhận thông báo push/alert khi shop tự xoá — chỉ thấy qua sự thay đổi trạng thái trong danh sách."
          ]
        },
        {
          "id": "AGA-SHOP-8",
          "jiraKey": "AGENCY-608",
          "title": "[AGA] Shop - Danh sách shop: Hiển thị link đăng nhập shop portal",
          "status": "draft",
          "userStory": "Là Agency Admin (Đại lý), tôi muốn thấy link đăng nhập shop portal ngay trên trang danh sách shop để tôi có thể dễ dàng sao chép và chia sẻ cho chủ shop mà không cần tìm ở nơi khác.",
          "notes": [],
          "userFlow": [
            "Agency Admin truy cập màn 'Quản lý shop'",
            "Hệ thống hiển thị banner 'Link đăng nhập shop' phía trên danh sách",
            "Agency Admin nhấn 'Copy' để sao chép URL vào clipboard",
            "Agency Admin chia sẻ URL cho chủ shop để đăng nhập"
          ],
          "acceptanceCriteria": [
            "AC1: Hệ thống hiển thị banner 'Link đăng nhập shop' cố định ở đầu trang 'Quản lý shop', phía dưới tiêu đề trang và phía trên thanh tìm kiếm. Banner luôn hiển thị bất kể trạng thái tìm kiếm hay danh sách shop.",
            "AC2: Banner hiển thị đầy đủ: label 'Link đăng nhập shop:', URL shop portal dạng link (click mở tab mới), nút 'Copy' ở phía phải.",
            "AC3: URL trong banner là URL shop portal dùng chung của đại lý — không phải URL riêng per shop. Tất cả shop thuộc cùng đại lý đều đăng nhập qua một URL duy nhất.",
            "AC4: Agency Admin nhấn 'Copy' → URL được sao chép toàn bộ vào clipboard. Nút hiển thị trạng thái 'Đã copy' trong 2 giây rồi tự reset về 'Copy'.",
            "AC5: Agency Admin click vào URL trong banner → hệ thống mở trang đăng nhập shop trong tab mới."
          ]
        }
      ]
    },
    {
      "key": "orders",
      "title": "Quản lý đơn hàng",
      "stories": []
    },
    {
      "key": "reconciliation",
      "title": "Đối soát & Chuyển khoản",
      "stories": [
        {
          "id": "AGA-RECON-2",
          "jiraKey": "",
          "title": "[AGA] Đối soát: Mapping chỉ số bảng \"Phiên GHN\" — nguồn dữ liệu và công thức tính",
          "userStory": "Là Agency Admin và dev team, tôi muốn biết rõ mỗi chỉ số hiển thị trong trang chi tiết \"Phiên GHN\" (AgencyReconciliationDetail.tsx) được lấy từ field nào trong mock data hoặc tính như thế nào tại runtime, để tin tưởng vào kết quả đối soát chênh lệch và xác định được điểm nào hệ thống đang thiếu dữ liệu so với file COD GHN thật.",
          "notes": [
            "GAP — Hoàn lại phí chuyển hoàn (4): File GHN thật có dòng này trong tổng quan phiên. Schema CarrierSession hiện không có field tương ứng. Cần bổ sung khi làm hệ thống thật.",
            "GAP — Ghi nợ cho phiên sau: File GHN thật tách thành dòng riêng biệt. outstandingDebt hiện chỉ phản ánh nợ tồn của phiên đang xem — cần thêm field carryForwardDebt nếu làm thật.",
            "GAP — Cột hành trình đơn: File GHN thật có 4 cột (Người nhận, Địa chỉ nhận, Ngày tạo, Ngày giao/trả) không có trong ItemRecord hiện tại.",
            "Field thừa chưa dùng: item.codFee và item.partialDeliveryFee có trong carrier-reconciliation-items.json nhưng không dùng ở UI. Cần confirm với BA.",
            "Hai nguồn tính totalFee: session.totalFee (lưu sẵn) và items.reduce(sum ghnFee) (runtime) cùng hiển thị trên hai card riêng — cần chọn source of truth khi làm hệ thống thật.",
            "shopName không hiển thị ở bảng phiên GHN (chỉ dùng ở AgencyReconciliationShopDetail.tsx) — thiết kế có chủ đích, không phải bug."
          ],
          "userFlow": [
            "[Session-level — map 1:1] ghnSessionCode → mã phiên; paymentDate → ngày; totalReconcile → Tổng đối soát; outstandingDebt → Nợ tồn; transferFee → Phí CK COD; netReceived → Thực nhận; totalFee → Phí dịch vụ",
            "[Session-level — tính runtime] Tổng đơn = items.length; Số lệch = items.filter(status !== MATCH).length; Card 'Tổng phí DV (GHN)' = items.reduce(sum ghnFee)",
            "[Session-level — map cứng] ghnShopId → tên khách hàng GHN tra qua GHN_SHOP_NAMES hardcode trong AgencyReconciliationDetail.tsx",
            "[Session-level — GAP] Hoàn lại phí chuyển hoàn (4) và Ghi nợ cho phiên sau: không có field tương ứng trong schema hiện tại",
            "[Item-level — map 1:1] orderCode, customerOrderCode, ghnStatus, ghnCOD/systemCOD, failedDeliveryCOD, prepaid, discount, deliveryFee, redeliveryFee, insuranceFee, returnFee, serviceFee/systemFee, totalReconcileItem",
            "[Item-level — chỉ số riêng hệ thống] item.status (MATCH/MISMATCH/NOT_FOUND) — kết quả so khớp COD và phí dịch vụ; không có trong file GHN gốc",
            "[Item-level — GAP] Người nhận, Địa chỉ nhận, Ngày tạo, Ngày giao/trả: có trong file GHN thật nhưng không có field tương ứng trong ItemRecord"
          ],
          "crossPlatformImpact": [],
          "acceptanceCriteria": [
            "AC1: Các chỉ số session-level map 1:1 từ JSON field (carrier-reconciliation.json) hiển thị đúng: ghnSessionCode → mã phiên, paymentDate → ngày, totalReconcile → Tổng đối soát, outstandingDebt → Nợ tồn, transferFee → Phí chuyển khoản COD, netReceived → Thực nhận, totalFee → Phí dịch vụ.",
            "AC2: Các chỉ số tính runtime được tính đúng: Tổng đơn = items.length; Số lệch = số item có status !== 'MATCH'; Card 'Tổng phí DV (GHN)' = items.reduce((sum, item) => sum + item.ghnFee, 0).",
            "AC3: item.status (MATCH/MISMATCH/NOT_FOUND) và 'Số lệch' là chỉ số riêng của hệ thống — không có trong file GHN gốc, được tính dựa trên so sánh ghnCOD vs systemCOD và serviceFee vs systemFee.",
            "AC4: Màu cảnh báo tô đỏ áp dụng đúng: ghnCOD tô đỏ khi ghnCOD !== systemCOD; serviceFee tô đỏ khi Math.abs(item.serviceFee) !== item.systemFee. Đơn NOT_FOUND hiển thị orderCode màu xám thay vì link xanh.",
            "AC5: Tên khách hàng GHN được tra qua map cứng GHN_SHOP_NAMES trong AgencyReconciliationDetail.tsx dựa trên session.ghnShopId. Nếu ghnShopId không có trong map → hiển thị fallback hoặc để trống."
          ],
          "status": "draft"
        },
        {
          "id": "AGA-RECON-1",
          "jiraKey": "",
          "title": "[AGA] Đối soát: Tạo phiên đối soát GHN",
          "userStory": "Là Agency Admin (Đại lý), tôi muốn tạo một phiên đối soát GHN mới bằng cách upload file thanh toán do GHN xuất ra, để hệ thống ghi nhận kỳ đối soát và chuẩn bị dữ liệu COD/cước phí cho việc xác nhận công nợ với GHN.",
          "notes": [
            "Hạn chế đã biết: ngày thanh toán hiện luôn được hệ thống tự set = ngày upload (hôm nay), không đọc từ nội dung file GHN thật — vì đây là mock demo, không parse nội dung file thật. Khi lên hệ thống thật cần làm rõ với BA: ngày thanh toán nên lấy từ file GHN hay do Agency Admin nhập tay.",
            "Việc tự động sinh \"phiên shop\" cho từng shop xảy ra ở bước xác nhận phiên (sau khi tạo), không phải ngay lúc tạo — xem story \"Xác nhận phiên đối soát GHN\" (chưa viết) và doc phien-shop.md.",
            "Doc cũ phien-nha-van-chuyen.md mô tả sai vài chi tiết (nói có kéo-thả và có ô chọn \"Ngày thanh toán GHN\") — đã đối chiếu lại đúng theo code hiện tại (AgencyReconciliation.tsx, UploadModal) khi viết story này; doc cũ cần được sửa lại ở lượt sau."
          ],
          "userFlow": [
            "Agency Admin truy cập \"Đối soát & Chuyển khoản\" → tab \"Phiên NVC\"",
            "Nhấn nút \"Tạo phiên [NVC/GHN]\" ở góc trên phải danh sách",
            "Modal \"Upload file đối soát GHN\" hiện ra",
            "Agency Admin nhấn để chọn file .xlsx, .xls, hoặc .csv xuất từ GHN (bắt buộc)",
            "Sau khi chọn, hệ thống hiển thị \"Mã phiên GHN\" lấy từ tên file (bỏ phần đuôi mở rộng)",
            "Agency Admin nhập \"Ghi chú\" (không bắt buộc)",
            "Nhấn \"Tải lên\" — hệ thống hiển thị tiến trình tải (progress bar); có thể \"Dừng tải\" giữa lúc đang tải",
            "Sau khi tải xong, phiên mới được tạo với ngày thanh toán = ngày hiện tại (hệ thống tự set), trạng thái \"Chờ xác nhận\", và xuất hiện đầu danh sách phiên"
          ],
          "acceptanceCriteria": [
            "AC1: Nút \"Tạo phiên [NVC/GHN]\" hiển thị ở góc trên phải tab \"Phiên NVC\"; bấm vào mở modal \"Upload file đối soát GHN\".",
            "AC2: Modal cho phép chọn 1 file .xlsx/.xls/.csv qua click chọn (chưa hỗ trợ kéo-thả file thật, dù khung chọn file có kiểu dáng dashed-border gợi ý dropzone).",
            "AC3: Nếu chưa chọn file mà nhấn \"Tải lên\" → hiển thị lỗi \"Vui lòng chọn file đối soát\", không cho tải lên.",
            "AC4: Sau khi chọn file, hệ thống hiển thị \"Mã phiên GHN\" (lấy từ tên file, bỏ đuôi mở rộng) kèm ghi chú \"Hệ thống sẽ tự động đọc thông tin phiên từ file sau khi tải lên\".",
            "AC5: Trường \"Ghi chú\" là tùy chọn.",
            "AC6: Khi tải lên, hệ thống hiển thị tiến trình dạng % (progress bar); Agency Admin có thể bấm \"Dừng tải\" để huỷ giữa chừng.",
            "AC7: Sau khi tải lên hoàn tất, phiên mới được tạo với: mã phiên dạng GHN{số thứ tự}, ngày thanh toán = ngày hiện tại, trạng thái \"Chờ xác nhận\", và xuất hiện đầu danh sách phiên.",
            "AC8: Phiên ở trạng thái \"Chờ xác nhận\" chưa bị khoá — vẫn có thể chỉnh sửa/xoá, khác với phiên đã \"Đã xác nhận\" (đã khoá dữ liệu)."
          ]
        }
      ]
    },
    {
      "key": "carrier-setup",
      "title": "Thiết lập NVC",
      "stories": [
        {
          "id": "AGA-CARRIER-1",
          "jiraKey": "",
          "title": "[AGA] Thiết lập NVC: Kết nối Shop ID GHN",
          "userStory": "Là Agency Admin (Đại lý), tôi muốn kết nối tài khoản Shop ID GHN vào hệ thống để có thể sử dụng dịch vụ vận chuyển của Giao Hàng Nhanh cho các shop thuộc đại lý.",
          "notes": [],
          "userFlow": [
            "Agency Admin truy cập menu \"Thiết lập NVC\" → tab \"Kết nối NVC\"",
            "Hệ thống hiển thị danh sách Shop ID GHN đã kết nối",
            "Agency Admin click \"Thêm Shop ID\"",
            "Hệ thống hiển thị modal nhập SĐT tài khoản GHN và Client ID",
            "Agency Admin nhập thông tin và click \"Kết nối\"",
            "Hệ thống gửi OTP về SĐT đã nhập",
            "Agency Admin nhập mã OTP 6 chữ số",
            "Hệ thống xác nhận và thêm Shop ID vào danh sách",
            "Agency Admin có thể ngắt kết nối một Shop ID bất kỳ"
          ],
          "acceptanceCriteria": [
            "AC1: Tab \"Kết nối NVC\" hiển thị danh sách Shop ID GHN đã kết nối với các cột: Tên cửa hàng, Shop ID, Số điện thoại, Ngày kết nối, Nút ngắt kết nối.",
            "AC2: Agency Admin có thể tìm kiếm Shop ID theo tên cửa hàng, Shop ID hoặc số điện thoại.",
            "AC3: Khi click \"Thêm Shop ID\", hệ thống hiển thị modal gồm 2 bước — Bước 1 (Form): Nhập SĐT tài khoản GHN và Client ID GHN. Bước 2 (OTP): Nhập mã OTP 6 chữ số gửi về SĐT.",
            "AC4: OTP gồm 6 ô nhập riêng biệt, tự động focus sang ô tiếp theo khi nhập xong.",
            "AC5: Sau khi gửi OTP, hệ thống bắt đầu đếm ngược 10 phút. Khi hết thời gian, Agency Admin có thể yêu cầu gửi lại OTP.",
            "AC6: Agency Admin có thể quay lại bước 1 để thay đổi số điện thoại.",
            "AC7: Khi click nút ngắt kết nối, hệ thống ngắt kết nối Shop ID tương ứng khỏi danh sách.",
            "AC8: Khi không có kết quả tìm kiếm, hệ thống hiển thị thông báo không tìm thấy."
          ]
        },
        {
          "id": "AGA-CARRIER-2",
          "jiraKey": "",
          "title": "[AGA] Thiết lập NVC: Quản lý gói dịch vụ",
          "userStory": "Là Agency Admin (Đại lý), tôi muốn xem và quản lý danh sách các gói dịch vụ vận chuyển để kiểm soát dịch vụ nào đang được kích hoạt cho đại lý và tạo mới gói dịch vụ khi cần.",
          "notes": [],
          "userFlow": [
            "Agency Admin truy cập menu \"Thiết lập NVC\" → tab \"Dịch vụ\"",
            "Hệ thống hiển thị danh sách gói dịch vụ",
            "Agency Admin có thể bật/tắt kích hoạt từng gói dịch vụ",
            "Agency Admin click vào tên gói để xem chi tiết (AGA-CARRIER-3)",
            "Agency Admin click \"Tạo mới dịch vụ\" để tạo gói mới",
            "Hệ thống hiển thị modal tạo gói dịch vụ",
            "Sau khi tạo thành công, hệ thống chuyển đến trang chi tiết gói vừa tạo"
          ],
          "acceptanceCriteria": [
            "AC1: Tab \"Dịch vụ\" hiển thị danh sách gói dịch vụ với các cột: Gói dịch vụ (tên), Mã dịch vụ NVC, NVC (nhà vận chuyển), Shop ID GHN (tên cửa hàng + ID), Vùng giao, Toggle kích hoạt. Cột Bảng giá và Tải trọng không hiển thị trên màn danh sách (được quản lý ở chi tiết dịch vụ).",
            "AC2: Agency Admin có thể bật/tắt kích hoạt từng gói dịch vụ bằng toggle.",
            "AC3: Agency Admin có thể click vào tên gói dịch vụ để xem trang chi tiết (AGA-CARRIER-3).",
            "AC4: Khi click \"Tạo mới dịch vụ\", hệ thống hiển thị modal gồm các trường: Mã gói (bắt buộc, monospace), Tên gói (bắt buộc), Mô tả, Kết nối Shop ID GHN (dropdown chọn từ danh sách đã kết nối).",
            "AC5: Nút \"Tạo gói dịch vụ\" bị disable khi chưa nhập Mã gói và Tên gói.",
            "AC6: Sau khi tạo thành công, hệ thống điều hướng đến trang chi tiết gói dịch vụ vừa tạo ở chế độ mới."
          ]
        },
        {
          "id": "AGA-CARRIER-3",
          "jiraKey": "",
          "title": "[AGA] Thiết lập NVC: Chi tiết gói dịch vụ",
          "userStory": "Là Agency Admin (Đại lý), tôi muốn xem và chỉnh sửa chi tiết một gói dịch vụ vận chuyển, bao gồm thông tin cơ bản, địa điểm khả dụng và địa điểm bị chặn để cấu hình vùng phủ dịch vụ phù hợp.",
          "notes": [],
          "userFlow": [
            "Agency Admin click vào tên gói dịch vụ trong danh sách (AGA-CARRIER-2)",
            "Hệ thống hiển thị trang chi tiết gói dịch vụ với 3 tab",
            "Agency Admin xem/chỉnh sửa thông tin tại tab \"Thông tin\"",
            "Agency Admin quản lý địa điểm khả dụng tại tab \"Địa điểm khả dụng\"",
            "Agency Admin quản lý địa điểm bị chặn tại tab \"Địa điểm chặn\"",
            "Agency Admin có thể quay lại danh sách dịch vụ bằng nút back"
          ],
          "acceptanceCriteria": [
            "AC1: Trang chi tiết có 3 tab: \"Thông tin\", \"Địa điểm khả dụng\", \"Địa điểm chặn\".",
            "AC2: Tab \"Thông tin\" hiển thị ở chế độ xem (view): Mã gói, Tên gói, Mô tả, Shop ID GHN kết nối. Phần Bảng giá hiển thị dạng card 1:1 — nếu đã gắn bảng giá thì hiện tên bảng giá, số tuyến, ngày tạo và nút \"Thay đổi\"; nếu chưa có bảng giá thì hiện cảnh báo màu vàng \"Chưa có bảng giá\" cùng nút \"Gắn bảng giá\". Agency Admin có thể click \"Chỉnh sửa\" để chuyển sang chế độ edit thông tin cơ bản.",
            "AC3: Ở chế độ edit, Agency Admin có thể sửa: Mã gói, Tên gói, Mô tả, Shop ID GHN. Có nút \"Lưu\" và \"Huỷ\".",
            "AC4: Tab \"Địa điểm khả dụng\" gồm 2 section: Lấy hàng và Giao hàng. Mỗi section hiển thị danh sách địa điểm và nút \"Thêm địa điểm\".",
            "AC5: Tab \"Địa điểm chặn\" có cấu trúc tương tự tab \"Địa điểm khả dụng\" nhưng dùng để cấu hình địa điểm không phục vụ.",
            "AC6: Agency Admin có thể thêm địa điểm vào danh sách Lấy hàng hoặc Giao hàng thông qua modal.",
            "AC7: Agency Admin có thể xoá địa điểm khỏi danh sách bằng nút xoá tương ứng.",
            "AC8: Nút back điều hướng về trang Thiết lập NVC."
          ]
        },
        {
          "id": "AGA-CARRIER-6",
          "jiraKey": "AGENCY-148",
          "title": "[AGA] Nhà vận chuyển - Tạo mới dịch vụ: Thông tin cơ bản",
          "userStory": "Là Agency Admin (Đại lý), tôi muốn nhập thông tin cơ bản khi tạo mới gói dịch vụ để định danh dịch vụ và gắn các Shop ID GHN sẽ thực hiện vận chuyển cho dịch vụ đó.",
          "notes": [
            "Dịch vụ mới tạo mặc định ở trạng thái chưa kích hoạt — Agency Admin bật toggle sau khi hoàn tất cấu hình",
            "Chưa gắn Shop ID GHN khi tạo vẫn được, có thể bổ sung ở trang chi tiết"
          ],
          "userFlow": [
            "Agency Admin nhấn Tạo dịch vụ mới từ tab Dịch vụ (AGENCY-68)",
            "Hệ thống hiển thị modal tạo dịch vụ",
            "Agency Admin nhập thông tin cơ bản và chọn Shop ID GHN",
            "Nhấn Tạo dịch vụ → hệ thống tạo và điều hướng sang trang chi tiết dịch vụ vừa tạo"
          ],
          "acceptanceCriteria": [
            "AC1: Modal tạo dịch vụ gồm các field: Mã dịch vụ (bắt buộc, font monospace, chỉ cho phép a-z A-Z 0-9 _, tối đa 50 ký tự, unique trong phạm vi đại lý), Tên dịch vụ (bắt buộc, tối đa 255 ký tự), Mô tả (tuỳ chọn, tối đa 500 ký tự), Shop ID GHN (tuỳ chọn, multi-select, chỉ liệt kê Shop ID đã kết nối).",
            "AC2: Nút Tạo dịch vụ disable khi chưa nhập Mã hoặc Tên dịch vụ.",
            "AC3: Mã dịch vụ trùng trong cùng đại lý → hiển thị lỗi inline Mã dịch vụ đã tồn tại, không cho submit.",
            "AC4: Field không hợp lệ → hiển thị lỗi inline ngay tại field, không cho submit.",
            "AC5: Tạo thành công → đóng modal, điều hướng sang trang chi tiết dịch vụ."
          ],
          "status": "draft"
        },
        {
          "id": "AGA-CARRIER-5",
          "jiraKey": "AGENCY-86",
          "title": "[AGA] Nhà vận chuyển - Dịch vụ: Xem danh sách gói dịch vụ",
          "userStory": "Là Agency Admin (Đại lý), tôi muốn xem danh sách các gói dịch vụ đại lý đang cung cấp để nắm toàn bộ dịch vụ đang hoạt động và quản lý chúng.",
          "notes": [
            "Dịch vụ chưa gắn Shop ID GHN nào → cột đó hiển thị —",
            "Toggle ở danh sách là shortcut của AGENCY-152, không cần vào chi tiết để bật/tắt"
          ],
          "userFlow": [
            "Agency Admin vào menu Thiết lập NVC → chọn tab Dịch vụ",
            "Hệ thống hiển thị danh sách gói dịch vụ của đại lý",
            "Agency Admin có thể tìm kiếm, xem trạng thái, nhấn tên dịch vụ để vào chi tiết (AGENCY-157), hoặc nhấn Tạo dịch vụ mới (AGENCY-148)"
          ],
          "acceptanceCriteria": [
            "AC1: Hiển thị danh sách dịch vụ thuộc đúng đại lý đang đăng nhập.",
            "AC2: Mỗi dòng hiển thị: Tên dịch vụ (link xanh bold), Mã dịch vụ, danh sách Shop ID GHN được gắn, toggle kích hoạt.",
            "AC3: Tìm kiếm theo tên hoặc mã, partial match, không phân biệt hoa/thường.",
            "AC4: Không có kết quả → hiển thị Không tìm thấy dữ liệu.",
            "AC5: Chưa có dịch vụ nào → empty state kèm nút Tạo dịch vụ mới.",
            "AC6: Nhấn tên dịch vụ → trang chi tiết dịch vụ.",
            "AC7: Nhấn Tạo dịch vụ mới → mở flow tạo dịch vụ (AGENCY-148)."
          ],
          "status": "draft"
        },
        {
          "id": "AGA-CARRIER-4",
          "jiraKey": "",
          "title": "[AGA] Thiết lập NVC: Bảng giá dịch vụ",
          "userStory": "Là Agency Admin (Đại lý), tôi muốn xem và quản lý cấu hình giá cho từng gói dịch vụ vận chuyển để kiểm soát chi phí ship theo tuyến và khu vực.",
          "notes": [],
          "userFlow": [
            "Agency Admin truy cập menu \"Thiết lập NVC\" → tab \"Bảng giá\"",
            "Hệ thống hiển thị segment chọn gói dịch vụ và bảng cấu hình giá",
            "Agency Admin chọn gói dịch vụ cần xem",
            "Hệ thống lọc và hiển thị danh sách cấu hình giá của gói đó",
            "Agency Admin click \"Chi tiết\" để xem chi tiết một cấu hình giá",
            "Agency Admin click \"Thêm cấu hình giá\" để tạo mới"
          ],
          "acceptanceCriteria": [
            "AC1: Tab \"Bảng giá\" hiển thị segment control để chọn gói dịch vụ (Giao hàng nhanh / Giao hàng tiêu chuẩn / Hàng cồng kềnh).",
            "AC2: Bảng giá hiển thị dạng đơn giản với 2 cột: Tên bảng giá và nút Chi tiết. Các thông tin chi tiết (số tuyến, trạng thái, dịch vụ được gắn) được xem trong trang chi tiết bảng giá, không hiển thị trên danh sách.",
            "AC3: Khi Agency Admin chọn gói dịch vụ khác, hệ thống lọc và hiển thị đúng cấu hình giá của gói đó.",
            "AC4: Khi không có cấu hình giá, hệ thống hiển thị thông báo \"Chưa có cấu hình giá\".",
            "AC5: Agency Admin có thể click \"Thêm cấu hình giá\" để tạo cấu hình giá mới cho gói đang chọn.",
            "AC6: Agency Admin có thể click \"Chi tiết\" để xem toàn bộ chi tiết cấu hình giá (bậc vượt cân, phụ phí)."
          ]
        },
        {
          "id": "AGA-CARRIER-5",
          "jiraKey": "",
          "title": "[AGA] Thiết lập NVC: Tạo bảng giá - Cấu hình phụ phí",
          "status": "draft",
          "userStory": "Là Agency Admin (Đại lý), tôi muốn cấu hình phụ phí cho từng tuyến trong bảng giá để xác định các khoản phí phát sinh ngoài cước phí cơ bản khi giao hàng.",
          "notes": [],
          "userFlow": [
            "Agency Admin đang tạo bảng giá mới, tại một tuyến bất kỳ",
            "Agency Admin click nút 'Phụ phí' trên thanh header của tuyến đó",
            "Hệ thống mở section phụ phí bên dưới, hiển thị danh sách 6 loại phụ phí — mặc định thu gọn",
            "Agency Admin click 'Thêm' bên cạnh loại phụ phí muốn cấu hình → form tương ứng mở ra",
            "Agency Admin nhập giá trị → phụ phí được lưu vào tuyến đó",
            "Nếu muốn xoá phụ phí đã cấu hình → click 'Xoá' → xác nhận trong modal"
          ],
          "acceptanceCriteria": [
            "AC1: Mỗi tuyến trong bảng giá có nút 'Phụ phí' ở góc phải header. Nút hiển thị badge số lượng loại phụ phí đã cấu hình. Click để mở/đóng section phụ phí của tuyến đó.",
            "AC2: Section phụ phí hiển thị đúng 6 loại theo thứ tự: (1) Phí bảo hiểm (khai giá), (2) Giao trả 1 phần, (3) Phí giao thất bại thu tiền, (4) Phí thu hộ, (5) Phí kích hoạt giao lại, (6) Phí hoàn hàng.",
            "AC3: Mặc định tất cả 6 loại thu gọn. Mỗi loại hiển thị: tên phụ phí + nút 'Thêm'. Khi đã cấu hình: thay nút 'Thêm' bằng nút 'Xoá' và form mở ra.",
            "AC4: Cấu trúc form theo loại: (a) Giao trả 1 phần và Phí giao thất bại thu tiền: nhập số tiền/đơn hàng (đồng). (b) Phí hoàn hàng: 2 radio button — 'Số tiền cố định' và '% cước phí tuyến', mỗi option có ô nhập riêng ngay cạnh. Ô của option không được chọn bị disable. Chọn option mới → reset giá trị về rỗng. (c) Phí bảo hiểm, Phí thu hộ, Phí kích hoạt giao lại: bảng nhiều mức.",
            "AC5: Bảng nhiều mức — cột Từ/Đến khác nhau theo loại: Phí bảo hiểm (giá trị khai giá từ/đến), Phí thu hộ (COD từ/đến), Phí kích hoạt giao lại (từ lần/đến lần). Cột phụ phí gồm: số fix (đồng) hoặc % — loại trừ nhau. Khi dùng %: xuất hiện ô 'Tối đa X đ' (không bắt buộc).",
            "AC6: Cột 'Từ' dòng thứ 2 trở đi tự động điền = giá trị 'Đến' dòng liền trước + 1, không chỉnh sửa được. Nút 'Thêm' thêm dòng mới phía dưới dòng hiện tại. Nút 'Xoá' xoá dòng (không hoạt động nếu chỉ còn 1 dòng).",
            "AC7: Click 'Xoá' phụ phí đã có dữ liệu → modal xác nhận 'Bạn có chắc muốn xoá cấu hình [tên phụ phí]? Dữ liệu đã nhập sẽ bị mất.' với nút Huỷ và Xoá. Click 'Xoá' khi chưa nhập → thu gọn trực tiếp, không cần xác nhận."
          ]
        },
        {
          "id": "AGA-CARRIER-6",
          "jiraKey": "AGENCY-250",
          "title": "[AGA] Thiết lập NVC: Tạo bảng giá - Cấu hình phụ phí Hoàn hàng",
          "status": "draft",
          "userStory": "Là Agency Admin (Đại lý), tôi muốn cấu hình phụ phí hoàn hàng cho từng tuyến trong bảng giá bằng cách chọn một trong hai hình thức tính phí — số tiền cố định hoặc phần trăm cước phí tuyến — để áp dụng đúng chính sách hoàn hàng của đại lý.",
          "notes": [],
          "userFlow": [
            "Agency Admin đang tạo bảng giá mới, mở section Phụ phí của một tuyến",
            "Tại mục Phí hoàn hàng, click 'Thêm'",
            "Hệ thống hiển thị form với 2 lựa chọn: Số tiền cố định và % cước phí tuyến",
            "Agency Admin chọn một hình thức và nhập giá trị vào ô tương ứng",
            "Nếu đổi sang hình thức khác → giá trị cũ bị xoá, nhập lại từ đầu"
          ],
          "acceptanceCriteria": [
            "AC1: Mục 'Phí hoàn hàng' hiển thị 2 radio button trên 2 dòng riêng: (1) Số tiền cố định — ô nhập + đ / đơn hàng. (2) % cước phí tuyến — ô nhập + % của cước phí tuyến / đơn hàng.",
            "AC2: Mặc định chọn 'Số tiền cố định'. Chỉ được chọn một trong hai — không thể chọn đồng thời cả hai.",
            "AC3: Ô nhập của option không được chọn bị vô hiệu hoá (nền xám, chữ nhạt, không nhập được). Ô nhập của option đang chọn hoạt động bình thường.",
            "AC4: Khi Agency Admin chuyển sang option khác → giá trị đang nhập bị xoá, ô nhập mới ở trạng thái rỗng để nhập lại.",
            "AC5: Nhãn trailing hiển thị đúng đơn vị: Số tiền cố định → 'đ / đơn hàng'. % cước phí tuyến → '% của cước phí tuyến / đơn hàng'.",
            "AC6: Giá trị hợp lệ là số dương. Placeholder gợi ý: 'VD: 10000' cho số tiền cố định, 'VD: 5' cho phần trăm."
          ]
        },
        {
          "id": "AGA-CARRIER-7",
          "jiraKey": "",
          "title": "[AGA] Thiết lập NVC: Bộ chọn nhà vận chuyển tích hợp trong từng tab",
          "status": "draft",
          "userStory": "Là Agency Admin, tôi muốn thấy bộ chọn nhà vận chuyển ngay bên trong từng tab (Kết nối, Dịch vụ, Bảng giá) thay vì một selector chung ở trên tất cả tab để tương tác rõ ràng hơn với dữ liệu của từng NVC trong mỗi ngữ cảnh.",
          "notes": [],
          "userFlow": [
            "Agency Admin truy cập menu \"Thiết lập NVC\"",
            "Mỗi tab (Kết nối / Dịch vụ / Bảng giá) hiển thị bộ chọn NVC \"Nhà vận chuyển: GHN | 247Express\" ở đầu nội dung tab",
            "Agency Admin chọn NVC tại một tab → nội dung tab lọc theo NVC được chọn",
            "Agency Admin chuyển sang tab khác → NVC đã chọn được giữ nguyên"
          ],
          "systemFlow": [
            "Khi trang CarrierSetup khởi tạo, selectedCarrier mặc định là \"GHN\"",
            "Component CarrierSelector được embed vào nội dung của cả 3 tab, đọc và ghi cùng một state duy nhất",
            "Khi user chọn NVC khác, selectedCarrier cập nhật → tất cả 3 tab tự re-render nội dung tương ứng",
            "Tab \"Bảng giá\" không còn bị disabled khi NVC chưa có Shop ID / ClientHubID; hiển thị banner cảnh báo nếu NVC chưa sẵn sàng"
          ],
          "crossPlatformImpact": [],
          "acceptanceCriteria": [
            "AC1: Mỗi tab (Kết nối / Dịch vụ / Bảng giá) hiển thị component CarrierSelector riêng với label \"Nhà vận chuyển:\" và 2 nút: \"GHN\" | \"247Express\" ở đầu nội dung tab.",
            "AC2: Khi Agency Admin chọn NVC trong bất kỳ tab nào, nội dung của tab đó lọc theo NVC được chọn.",
            "AC3: Trạng thái NVC đang chọn được chia sẻ giữa các tab (shared state) — chuyển tab không reset lại về GHN.",
            "AC4: Tab \"Bảng giá\" luôn có thể click bất kể NVC đã có Shop ID / ClientHubID hay chưa — không còn bị disabled.",
            "AC5: Khi NVC chưa sẵn sàng (GHN chưa có Shop ID kết nối, hoặc 247Express chưa được kích hoạt / chưa có ClientHubID), tab \"Bảng giá\" hiển thị banner cảnh báo thay vì chặn truy cập.",
            "AC6: CarrierSelector là một component tái sử dụng, được embed vào cả 3 tab từ cùng một implementation — không duplicate code selector."
          ]
        },
        {
          "id": "AGA-CARRIER-8",
          "jiraKey": "",
          "title": "[AGA] Thiết lập NVC - Bảng giá 247Express: Selector dịch vụ và cấu trúc zone block",
          "status": "draft",
          "userStory": "Là Agency Admin, tôi muốn tạo bảng giá cho 247Express bằng cách chọn từng dịch vụ cụ thể và cấu hình giá theo từng zone dưới dạng card riêng biệt để mỗi dịch vụ có cấu hình độc lập và không ảnh hưởng lẫn nhau trong cùng một lần tạo bảng giá.",
          "notes": [
            "Kiến trúc zone block tương đồng với PricingCreate.tsx (GHN \"tuyến\" route blocks) — tham khảo pattern đó khi implement",
            "3 dịch vụ 247Express là KHÔNG thể hoán đổi — giá vốn và cấu trúc zone của mỗi dịch vụ là khác nhau hoàn toàn"
          ],
          "userFlow": [
            "Agency Admin truy cập Thiết lập NVC → tab Bảng giá → chọn NVC \"247Express\" → click \"Thêm bảng giá\"",
            "Hệ thống mở trang \"Tạo bảng giá 247Express\"",
            "Trang hiển thị 3 tab dịch vụ: \"Chuyển phát nhanh\" / \"Chuyển phát nhanh tiết kiệm\" / \"Chuyển phát đường bộ\"",
            "Agency Admin chọn một tab dịch vụ → nội dung hiển thị các zone block tương ứng",
            "Mỗi zone được hiển thị dạng card có viền trái màu sắc, tên zone, và các field nhập giá bán kèm giá vốn tham chiếu",
            "Agency Admin cấu hình lần lượt các dịch vụ → dữ liệu mỗi dịch vụ được lưu độc lập khi chuyển tab",
            "Agency Admin hoàn tất và submit bảng giá"
          ],
          "systemFlow": [
            "Trang khởi tạo state độc lập cho từng dịch vụ (3 slice riêng biệt)",
            "Khi chuyển tab dịch vụ, hệ thống giữ nguyên dữ liệu tab cũ và load dữ liệu tab mới từ state",
            "\"Chuyển phát nhanh\" có 6 zone, \"Chuyển phát nhanh tiết kiệm\" và \"Chuyển phát đường bộ\" mỗi dịch vụ có 5 zone",
            "Mỗi zone được render dưới dạng card với toggle \"Vượt cân\" (và \"Phụ phí\" riêng cho Chuyển phát nhanh)",
            "Khi Agency Admin submit, hệ thống validate và lưu toàn bộ 3 dịch vụ"
          ],
          "crossPlatformImpact": [],
          "acceptanceCriteria": [
            "AC1: Trang \"Tạo bảng giá 247Express\" hiển thị tiêu đề bảng giá kèm ghi chú tham chiếu hợp đồng số 1231/2026/HĐDV-247.",
            "AC2: Trang có 3 tab dịch vụ ở đầu: \"Chuyển phát nhanh\" / \"Chuyển phát nhanh tiết kiệm\" / \"Chuyển phát đường bộ\". Mặc định chọn tab đầu tiên.",
            "AC3: Dữ liệu từng tab dịch vụ lưu độc lập — Agency Admin có thể cấu hình cả 3 dịch vụ trong cùng một lần tạo bảng giá mà không mất dữ liệu khi chuyển tab.",
            "AC4: Mỗi zone được render dưới dạng card riêng biệt có viền trái màu sắc, hiển thị tên zone, và các field nhập giá bán bên cạnh label giá vốn tham chiếu.",
            "AC5: Tab \"Chuyển phát nhanh\" hiển thị 6 zone card. Tab \"Chuyển phát nhanh tiết kiệm\" và \"Chuyển phát đường bộ\" mỗi tab hiển thị 5 zone card.",
            "AC6: Mỗi zone card có toggle \"Vượt cân\" — khi bật, hiển thị form cấu hình cước vượt cân theo cú pháp \"Tăng X đồng trên mỗi Y gram\" (nhất quán với PricingCreate GHN).",
            "AC7: Tab \"Chuyển phát nhanh\" có thêm toggle \"Phụ phí\" trên mỗi zone card; tab \"Chuyển phát nhanh tiết kiệm\" và \"Chuyển phát đường bộ\" không có toggle này."
          ]
        },
        {
          "id": "AGA-CARRIER-9",
          "jiraKey": "",
          "title": "[AGA] Thiết lập NVC - Bảng giá 247Express: Dịch vụ Chuyển phát nhanh",
          "status": "draft",
          "userStory": "Là Agency Admin, tôi muốn cấu hình bảng giá chi tiết cho dịch vụ \"Chuyển phát nhanh\" của 247Express theo 6 vùng giao và các bậc khối lượng (gram bracket) để xác định giá bán phù hợp với chi phí của từng tuyến.",
          "notes": [],
          "userFlow": [
            "Agency Admin mở trang \"Tạo bảng giá 247Express\" → tab \"Chuyển phát nhanh\"",
            "Hệ thống hiển thị phần cấu hình \"Mốc khối lượng\" chung dùng cho tất cả zone (mặc định: 50g, 100g, 200g, 500g, 1000g, 2000g)",
            "Agency Admin thêm, xoá hoặc chỉnh sửa các mốc → tất cả 6 zone card cập nhật đồng bộ",
            "Hệ thống hiển thị 6 zone card: Nội tỉnh 1, Nội tỉnh 2, Đến 300km, Trên 300km, Nội tỉnh 1 HCM↔ĐN/ĐN↔HN, Nội tỉnh 1 HCM↔HN",
            "Agency Admin nhập giá bán tại từng mốc khối lượng và 2 mức \"+500gr tiếp theo\" (band 2–10kg và >10kg)",
            "Mỗi ô nhập giá bán hiển thị label \"Giá vốn: X đ\" tham chiếu bên cạnh"
          ],
          "systemFlow": [
            "Phần \"Mốc khối lượng\" là shared config — khi thay đổi, hệ thống cập nhật số hàng của tất cả 6 zone card",
            "Mỗi zone card render bảng giá theo danh sách mốc hiện tại + 2 hàng bổ sung \"+500gr tiếp theo\" (2–10kg và >10kg)",
            "Field \"Giá bán\" nhận số nguyên dương, hiển thị format phân cách nghìn (.)",
            "Giá vốn là dữ liệu tham chiếu cố định từ hợp đồng 247Express, không do Agency Admin nhập"
          ],
          "crossPlatformImpact": [],
          "acceptanceCriteria": [
            "AC1: Tab \"Chuyển phát nhanh\" có phần cấu hình \"Mốc khối lượng\" chung dùng cho tất cả zone: các mốc gram mặc định 50g, 100g, 200g, 500g, 1000g, 2000g. Agency Admin có thể thêm, xoá, chỉnh sửa mốc. Thay đổi mốc → tất cả 6 zone card cập nhật đồng bộ ngay lập tức.",
            "AC2: 6 zone card hiển thị đúng thứ tự và tên: (1) Nội tỉnh 1, (2) Nội tỉnh 2, (3) Đến 300km, (4) Trên 300km, (5) Nội tỉnh 1 HCM↔ĐN / ĐN↔HN, (6) Nội tỉnh 1 HCM↔HN.",
            "AC3: Mỗi zone card hiển thị bảng giá theo mốc khối lượng. Mỗi hàng gồm: nhãn mốc khối lượng, ô nhập \"Giá bán\" (đồng, bắt buộc khi zone được kích hoạt), label \"Giá vốn: X đ\" tham chiếu từ 247Express.",
            "AC4: Ngoài các mốc khối lượng, mỗi zone có thêm 2 hàng \"+500gr tiếp theo\": một cho band 2–10kg và một cho >10kg, mỗi hàng có ô nhập giá bán và giá vốn tham chiếu riêng.",
            "AC5: Mỗi zone card có toggle \"Vượt cân\" — khi bật, hiển thị form cấu hình cước vượt cân theo cú pháp \"Tăng X đồng trên mỗi Y gram\".",
            "AC6: Mỗi zone card có toggle \"Phụ phí\" — khi bật, mở section phụ phí của zone đó (chi tiết tại AGA-CARRIER-10)."
          ]
        },
        {
          "id": "AGA-CARRIER-10",
          "jiraKey": "",
          "title": "[AGA] Thiết lập NVC - Bảng giá 247Express: Phụ phí & Dịch vụ gia tăng (Chuyển phát nhanh)",
          "status": "draft",
          "userStory": "Là Agency Admin, tôi muốn xem dữ liệu phụ phí theo hợp đồng và tính tổng phụ phí theo điều kiện thực tế (loại hàng, ngoại thành, xe nâng...) trên từng zone của dịch vụ Chuyển phát nhanh 247Express để tham chiếu khi cấu hình giá bán.",
          "notes": [
            "Phụ phí và dịch vụ gia tăng chỉ áp dụng cho dịch vụ \"Chuyển phát nhanh\" — không có cho \"Chuyển phát nhanh tiết kiệm\" và \"Chuyển phát đường bộ\""
          ],
          "userFlow": [
            "Agency Admin ở tab \"Chuyển phát nhanh\" của trang tạo bảng giá 247Express",
            "Tại một zone card, Agency Admin click toggle \"Phụ phí\" → section phụ phí mở ra bên dưới zone đó",
            "Agency Admin chọn loại hàng hoá, tích checkbox cước hoàn, ngoại thành, nhập số lượng xe nâng",
            "Hệ thống tự tính và hiển thị tổng phụ phí dựa trên các lựa chọn",
            "Trang cũng hiển thị các bảng tham chiếu cố định: Dịch vụ gia tăng nhanh, Phí đóng gói, Dịch vụ gia tăng khác"
          ],
          "systemFlow": [
            "Tỷ lệ phụ phí (%, công thức, mức phí cố định) được lưu trong config của trang — không do Agency Admin nhập",
            "Khi Agency Admin chọn các điều kiện, hệ thống áp công thức từ hợp đồng để tính tổng phụ phí",
            "Các bảng tham chiếu (Dịch vụ gia tăng nhanh, Phí đóng gói, Dịch vụ gia tăng khác) hiển thị read-only, không lưu vào bảng giá"
          ],
          "crossPlatformImpact": [],
          "acceptanceCriteria": [
            "AC1: Mỗi zone card trong tab \"Chuyển phát nhanh\" có toggle \"Phụ phí\". Khi mở, section hiển thị: dropdown loại hàng hoá (hàng thường / nguyên khối / quá khổ), checkbox \"Cước chuyển hoàn\", checkbox \"Ngoại thành\" (phụ phí 20%), ô nhập số lượng xe nâng, tổng phụ phí được tính tự động.",
            "AC2: Dữ liệu phụ phí hiển thị đúng theo hợp đồng 1231/2026/HĐDV-247: phụ phí ngoại thành 20%, phụ phí nhiên liệu 24% (hiệu lực 01/05/2026–31/07/2026), phí hàng nguyên khối 10%, phí hàng quá khổ 10%, phí thuê xe nâng 625.000đ/lần.",
            "AC3: Trang hiển thị bảng tham chiếu \"Dịch vụ gia tăng nhanh\" với 2 loại: Phát trong ngày và Phát hẹn giờ — dưới dạng read-only.",
            "AC4: Trang hiển thị bảng tham chiếu \"Phí đóng gói\" theo vật liệu đóng gói — dưới dạng read-only.",
            "AC5: Trang hiển thị bảng \"Dịch vụ gia tăng khác\" với 21 dịch vụ bổ sung (bao gồm: Chụp hình, Khai giá hàng hóa, Hàng đông lạnh, Phí an ninh, và các dịch vụ khác theo hợp đồng) — dưới dạng read-only.",
            "AC6: Tất cả dữ liệu trong các bảng tham chiếu là read-only — Agency Admin không thể chỉnh sửa."
          ]
        },
        {
          "id": "AGA-CARRIER-11",
          "jiraKey": "",
          "title": "[AGA] Thiết lập NVC - Bảng giá 247Express: Chuyển phát nhanh tiết kiệm & Chuyển phát đường bộ",
          "status": "draft",
          "userStory": "Là Agency Admin, tôi muốn cấu hình bảng giá cho dịch vụ \"Chuyển phát nhanh tiết kiệm\" và \"Chuyển phát đường bộ\" của 247Express theo 5 vùng giao với cơ chế giá base đến 5kg cộng thêm theo 4 band khối lượng để xác định giá bán phù hợp với từng tuyến.",
          "notes": [],
          "userFlow": [
            "Agency Admin mở trang \"Tạo bảng giá 247Express\" → tab \"Chuyển phát nhanh tiết kiệm\" hoặc \"Chuyển phát đường bộ\"",
            "Hệ thống hiển thị 5 zone card: Nội tỉnh 1, Nội tỉnh 2, Đến 300km, Đến 1000km, Trên 1000km",
            "Mỗi zone card có: ô nhập giá \"đến 5kg\" (base price) và 4 ô \"giá cộng thêm mỗi 1kg tiếp theo\" chia theo band",
            "Mỗi ô hiển thị giá vốn tham chiếu tương ứng",
            "Agency Admin nhập giá bán tại từng ô và có thể bật toggle \"Vượt cân\" nếu cần"
          ],
          "systemFlow": [
            "5 zone card được render cố định theo schema của từng dịch vụ — không dùng \"Mốc khối lượng\" chung như dịch vụ Chuyển phát nhanh",
            "Mỗi zone có cấu trúc cố định: 1 ô \"đến 5kg\" + 4 ô \"cộng thêm 1kg\" (đến 50kg / đến 200kg / đến 500kg / trên 500kg)",
            "Giá vốn là dữ liệu tham chiếu cố định từ hợp đồng — khác nhau giữa 2 dịch vụ",
            "Dữ liệu tab tiết kiệm và tab đường bộ lưu hoàn toàn độc lập"
          ],
          "crossPlatformImpact": [],
          "acceptanceCriteria": [
            "AC1: Tab \"Chuyển phát nhanh tiết kiệm\" và tab \"Chuyển phát đường bộ\" mỗi tab hiển thị 5 zone card theo đúng thứ tự: (1) Nội tỉnh 1, (2) Nội tỉnh 2, (3) Đến 300km, (4) Đến 1000km, (5) Trên 1000km.",
            "AC2: Mỗi zone card có 2 phần cấu hình: (1) Giá \"đến 5kg\" (base price, 1 ô nhập giá bán + giá vốn tham chiếu), (2) \"Giá cộng thêm mỗi 1kg tiếp theo\" với 4 band: đến 50kg / đến 200kg / đến 500kg / trên 500kg — mỗi band có ô nhập giá bán và giá vốn tham chiếu.",
            "AC3: Hai dịch vụ có cùng cấu trúc zone nhưng giá vốn (247Express cost) khác nhau — hệ thống hiển thị đúng giá vốn theo từng dịch vụ đang chọn.",
            "AC4: Cả 2 tab đều hiển thị ghi chú rõ ràng: \"Chưa có dữ liệu phụ phí cho dịch vụ này\" — không hiển thị toggle \"Phụ phí\" và không tái sử dụng dữ liệu phụ phí của dịch vụ Chuyển phát nhanh.",
            "AC5: Mỗi zone card có toggle \"Vượt cân\" — khi bật, hiển thị form cấu hình cước vượt cân theo cú pháp \"Tăng X đồng trên mỗi Y gram\".",
            "AC6: Dữ liệu của tab Chuyển phát nhanh tiết kiệm và tab Chuyển phát đường bộ lưu độc lập với nhau và với tab Chuyển phát nhanh."
          ]
        }
      ]
    },
    {
      "key": "he-thong",
      "title": "Hệ thống",
      "stories": [
        {
          "id": "AGA-HT-1",
          "jiraKey": "AGENCY-609",
          "title": "[HỆ THỐNG] Cập nhật danh sách đầu số điện thoại hợp lệ",
          "status": "draft",
          "userStory": "Là người dùng (Shop / Agency Admin / Super Admin), tôi muốn có thể nhập số điện thoại với các đầu số mới và hợp lệ của tất cả nhà mạng Việt Nam để hệ thống không từ chối các SĐT thực tế đang dùng.",
          "notes": [
            "Danh sách đầu số chuẩn theo config GHN (valid_mobilephone_headers), không phải danh sách Bộ TT&TT",
            "Đầu số 0868 → prefix 086 đã có trong Viettel, nên thực ra không bị thiếu nếu validate 3 số đầu",
            "Điện thoại cố định (valid_homephone_headers) phức tạp hơn → tách task riêng",
            "Cần confirm với backend team về format lưu SĐT trong DB: có normalize trước khi lưu không?"
          ],
          "userFlow": [
            "Người dùng mở bất kỳ form có field SĐT",
            "Nhập số điện thoại 10 chữ số",
            "Hệ thống validate khi blur hoặc khi submit: đủ 10 chữ số + 3 chữ số đầu nằm trong danh sách hợp lệ",
            "Hợp lệ → cho phép tiếp tục",
            "Không hợp lệ → hiển thị lỗi: \"Số điện thoại không hợp lệ. Vui lòng kiểm tra lại đầu số.\""
          ],
          "acceptanceCriteria": [
            "AC1: Các đầu số sau được chấp nhận (trước đây bị từ chối): 071, 072, 073, 080, 051, 053, 054, 055, 057.",
            "AC2: Các đầu số không tồn tại (ví dụ: 011, 044, 060) bị từ chối với message: \"Số điện thoại không hợp lệ. Vui lòng kiểm tra lại đầu số.\"",
            "AC3: Validation áp dụng nhất quán cho tất cả field SĐT trên 3 platform — không có field nào dùng rule cũ.",
            "AC4: SĐT 9 số, 11 số, hoặc có ký tự đặc biệt đều bị từ chối.",
            "AC5: Logic validate được tập trung tại 1 utility function, không hardcode riêng lẻ tại từng form.",
            "AC6: Không có regression — các đầu số hiện tại đang hợp lệ vẫn tiếp tục được chấp nhận."
          ]
        }
      ]
    }
  ],
  "history": [
    {
      "version": "0.1.0",
      "date": "2026-04-15",
      "summary": "Khởi tạo document"
    },
    {
      "version": "1.0.0",
      "date": "2026-04-16",
      "summary": "Cập nhật đầy đủ nội dung từ BRD: Login/Logout, Cài đặt GHN, Quản lý Shop (5 stories), và toàn bộ sections còn lại"
    },
    {
      "version": "1.1.0",
      "date": "2026-04-17",
      "summary": "v0.8.0 — Cấu trúc Service–Shop–PriceTable: thêm AGA-SHOP-6, cập nhật AC cho AGA-CARRIER-2, AGA-CARRIER-3, AGA-CARRIER-4"
    }
  ]
}